paraty_commit/.pre-commit-config.yaml
paraty_commit/__init__.py
paraty_commit/mypy.ini
paraty_commit/precommit.py
paraty_commit/pylintrc
paraty_commit-0.2.4.dist-info/LICENSE
paraty_commit-0.2.4.dist-info/METADATA
paraty_commit-0.2.4.dist-info/WHEEL
paraty_commit-0.2.4.dist-info/entry_points.txt
paraty_commit-0.2.4.dist-info/top_level.txt
paraty_commit-0.2.4.dist-info/RECORD
