Metadata-Version: 2.1
Name: paraty-commit
Version: 0.2.4
Summary: Una biblioteca personalizada
Author: José Luis Villada
Author-email: jlvillada@paratytech.com
Requires-Python: >=3.7
License-File: LICENSE
Requires-Dist: colorama
Requires-Dist: pylint ==2.15.10
Requires-Dist: rich
